godfather/__init__.py
godfather/__main__.py
godfather/emails.py
godfather/mailgun.py
godfather/main.py
godfather/moderator.py
godfather/server.py
godfather/emails/died.html
godfather/emails/end_of_phase.html
godfather/emails/role_announcement.html
godfather/emails/welcome.html
godfather/static/styles.css
godfather/templates/footer.html
godfather/templates/header.html
godfather/templates/patch.py
godfather/templates/players.html
godfather/templates/setup.py
godfather/templates/status.html
godfather-1.0.0.dist-info/DESCRIPTION.rst
godfather-1.0.0.dist-info/METADATA
godfather-1.0.0.dist-info/RECORD
godfather-1.0.0.dist-info/WHEEL
godfather-1.0.0.dist-info/entry_points.txt
godfather-1.0.0.dist-info/metadata.json
godfather-1.0.0.dist-info/top_level.txt
